<?xml version='1.0' encoding='UTF-8'?><Output><inputFile>src/main/resources/data/input_data.txt</inputFile><references><references numReference="1460100040" size="27" price="45.12" color="R"/><references numReference="1460900848" size="145" price="12.0" color="G"/><references numReference="1462100044" size="19" price="5.56" color="G"/><references numReference="1462100403" size="97" price="105.23" color="B"/></references><errors><errors item="4" message="The color reference is wrong... please check the input value">1462100403;A;100.1;9</errors></errors></Output>